setup.py
pyspc/__init__.py
pyspc/pyspc.py
pyspc/results.py
pyspc/rules.py
pyspc.egg-info/PKG-INFO
pyspc.egg-info/SOURCES.txt
pyspc.egg-info/dependency_links.txt
pyspc.egg-info/not-zip-safe
pyspc.egg-info/requires.txt
pyspc.egg-info/top_level.txt
pyspc/ccharts/__init__.py
pyspc/ccharts/c.py
pyspc/ccharts/ccharts.py
pyspc/ccharts/cusum.py
pyspc/ccharts/ewma.py
pyspc/ccharts/hotelling.py
pyspc/ccharts/imrmr.py
pyspc/ccharts/imrr.py
pyspc/ccharts/imrstd.py
pyspc/ccharts/imrx.py
pyspc/ccharts/mr.py
pyspc/ccharts/np.py
pyspc/ccharts/p.py
pyspc/ccharts/tables.py
pyspc/ccharts/u.py
pyspc/ccharts/xbar_rbar.py
pyspc/ccharts/xbar_sbar.py
pyspc/sampledata/PaintMaterial.csv
pyspc/sampledata/Viscosidade.csv
pyspc/sampledata/__init__.py
pyspc/sampledata/canjuice.csv
pyspc/sampledata/chemical.csv
pyspc/sampledata/circuits.csv
pyspc/sampledata/dados.csv
pyspc/sampledata/diameter.csv
pyspc/sampledata/experiment.csv
pyspc/sampledata/grams.csv
pyspc/sampledata/hotelling.csv
pyspc/sampledata/inspection.csv
pyspc/sampledata/newproduct.csv
pyspc/sampledata/parts.csv
pyspc/sampledata/pistonrings.csv
pyspc/sampledata/sandbox.csv
pyspc/sampledata/sizes.csv
pyspc/sampledata/thickness.csv
pyspc/sampledata/waitingTime.csv
tests/__init__.py
tests/pyspc_test.py