Metadata-Version: 1.1
Name: pyspc
Version: 0.4
Summary: Statistical Process Control Charts Library for Humans
Home-page: https://github.com/carlosqsilva/pyspc
Author: Carlos Silva
Author-email: carlosqsilva@outlook.com
License: GPLv3
Keywords: SPC QCC CEQ CEP UEPA
Platform: UNKNOWN
Classifier: Development Status :: 4 - Beta
Classifier: Intended Audience :: Developers
Classifier: Intended Audience :: Science/Research
Classifier: License :: OSI Approved :: GNU General Public License v3 (GPLv3)
Classifier: Topic :: Scientific/Engineering
Classifier: Operating System :: Microsoft :: Windows
Classifier: Operating System :: POSIX :: Linux
Classifier: Operating System :: MacOS
Classifier: Programming Language :: Python :: 3.3
Classifier: Programming Language :: Python :: 3.4
Classifier: Programming Language :: Python :: 3.5
Classifier: Topic :: Software Development :: Libraries :: Python Modules
